[
  {
    "name": 215,
    "rule_set": "SWIMWEAR-WOMEN-ALPHA-REG",
    "pom": "POM-089",
    "increment_cm": 0.75,
    "grading_type": "LINEAR",
    "increment_above_xl": 0.75,
    "direction_note": "Leg opening bany.",
    "tolerance_check": "Tol. prod 0.75 = grade — revisar",
    "client": null,
    "rule_source": "SECTOR_STANDARD",
    "is_active": 1,
    "notes": null
  },
  {
    "name": 214,
    "rule_set": "SWIMWEAR-WOMEN-ALPHA-REG",
    "pom": "POM-088",
    "increment_cm": 0.5,
    "grading_type": "LINEAR",
    "increment_above_xl": 0.5,
    "direction_note": "Entrecuix bany: creixement mínim.",
    "tolerance_check": "Tol. prod 0.5 = grade — revisar",
    "client": null,
    "rule_source": "SECTOR_STANDARD",
    "is_active": 1,
    "notes": null
  },
  {
    "name": 213,
    "rule_set": "SWIMWEAR-WOMEN-ALPHA-REG",
    "pom": "POM-050",
    "increment_cm": 1.5,
    "grading_type": "LINEAR",
    "increment_above_xl": 1.5,
    "direction_note": "Cinturó bany: 3cm circumf/talla.",
    "tolerance_check": "Tol. prod 1.0 ≤ grade 1.5",
    "client": null,
    "rule_source": "SECTOR_STANDARD",
    "is_active": 1,
    "notes": null
  },
  {
    "name": 212,
    "rule_set": "SWIMWEAR-WOMEN-ALPHA-REG",
    "pom": "POM-085",
    "increment_cm": 1.0,
    "grading_type": "LINEAR",
    "increment_above_xl": 1.0,
    "direction_note": "Copa: creix 1cm/talla.",
    "tolerance_check": "Tol. prod 0.5 ≤ grade 1.0",
    "client": null,
    "rule_source": "SECTOR_STANDARD",
    "is_active": 1,
    "notes": null
  },
  {
    "name": 211,
    "rule_set": "TOPS-KNIT-TGIRL-EU-HEIGHT-REG",
    "pom": "POM-009",
    "increment_cm": 2.0,
    "grading_type": "LINEAR",
    "increment_above_xl": 2.0,
    "direction_note": "Teen girl: longitud creix cada talla.",
    "tolerance_check": "Tol. prod 1.5 ≤ grade 2.0",
    "client": null,
    "rule_source": "SECTOR_STANDARD",
    "is_active": 1,
    "notes": null
  },
  {
    "name": 210,
    "rule_set": "TOPS-KNIT-TGIRL-EU-HEIGHT-REG",
    "pom": "POM-001",
    "increment_cm": 2.0,
    "grading_type": "LINEAR",
    "increment_above_xl": 2.0,
    "direction_note": "Teen girl: pit 4cm circumf.",
    "tolerance_check": "Tol. prod 1.0 ≤ grade 2.0",
    "client": null,
    "rule_source": "SECTOR_STANDARD",
    "is_active": 1,
    "notes": null
  },
  {
    "name": 209,
    "rule_set": "TOPS-KNIT-TBOY-EU-HEIGHT-REG",
    "pom": "POM-009",
    "increment_cm": 2.0,
    "grading_type": "LINEAR",
    "increment_above_xl": 2.0,
    "direction_note": "Teen: longitud entre kids i adult.",
    "tolerance_check": "Tol. prod 1.5 ≤ grade 2.0",
    "client": null,
    "rule_source": "SECTOR_STANDARD",
    "is_active": 1,
    "notes": null
  },
  {
    "name": 208,
    "rule_set": "TOPS-KNIT-TBOY-EU-HEIGHT-REG",
    "pom": "POM-001",
    "increment_cm": 2.5,
    "grading_type": "LINEAR",
    "increment_above_xl": 2.5,
    "direction_note": "Teen boy: pit creix com adult.",
    "tolerance_check": "Tol. prod 1.0 ≤ grade 2.5",
    "client": null,
    "rule_source": "SECTOR_STANDARD",
    "is_active": 1,
    "notes": null
  },
  {
    "name": 207,
    "rule_set": "TOPS-KNIT-JBOY-EU-HEIGHT-REG",
    "pom": "POM-020",
    "increment_cm": 1.5,
    "grading_type": "LINEAR",
    "increment_above_xl": 1.5,
    "direction_note": "Junior: màniga creix cada talla.",
    "tolerance_check": "Tol. prod 1.0 ≤ grade 1.5",
    "client": null,
    "rule_source": "SECTOR_STANDARD",
    "is_active": 1,
    "notes": null
  },
  {
    "name": 206,
    "rule_set": "TOPS-KNIT-JBOY-EU-HEIGHT-REG",
    "pom": "POM-009",
    "increment_cm": 2.0,
    "grading_type": "LINEAR",
    "increment_above_xl": 2.0,
    "direction_note": "Junior: longitud creix cada talla.",
    "tolerance_check": "Tol. prod 1.5 ≤ grade 2.0",
    "client": null,
    "rule_source": "SECTOR_STANDARD",
    "is_active": 1,
    "notes": null
  },
  {
    "name": 205,
    "rule_set": "TOPS-KNIT-JBOY-EU-HEIGHT-REG",
    "pom": "POM-001",
    "increment_cm": 2.0,
    "grading_type": "LINEAR",
    "increment_above_xl": 2.0,
    "direction_note": "Junior: pit +4cm/talla.",
    "tolerance_check": "Tol. prod 1.0 ≤ grade 2.0",
    "client": null,
    "rule_source": "SECTOR_STANDARD",
    "is_active": 1,
    "notes": null
  },
  {
    "name": 204,
    "rule_set": "TOPS-KNIT-BABY-EU-HEIGHT-REG",
    "pom": "POM-030",
    "increment_cm": 0.5,
    "grading_type": "LINEAR",
    "increment_above_xl": 0.5,
    "direction_note": "Kids: coll creix proporcionalment més.",
    "tolerance_check": "Tol. prod 0.5 = grade — revisar",
    "client": null,
    "rule_source": "SECTOR_STANDARD",
    "is_active": 1,
    "notes": null
  },
  {
    "name": 203,
    "rule_set": "TOPS-KNIT-BABY-EU-HEIGHT-REG",
    "pom": "POM-020",
    "increment_cm": 1.5,
    "grading_type": "LINEAR",
    "increment_above_xl": 1.5,
    "direction_note": "Baby: màniga creix cada talla.",
    "tolerance_check": "Tol. prod 1.0 ≤ grade 1.5",
    "client": null,
    "rule_source": "SECTOR_STANDARD",
    "is_active": 1,
    "notes": null
  },
  {
    "name": 202,
    "rule_set": "TOPS-KNIT-BABY-EU-HEIGHT-REG",
    "pom": "POM-009",
    "increment_cm": 2.5,
    "grading_type": "LINEAR",
    "increment_above_xl": 2.5,
    "direction_note": "Baby: longitud creix molt.",
    "tolerance_check": "Tol. prod 1.5 ≤ grade 2.5",
    "client": null,
    "rule_source": "SECTOR_STANDARD",
    "is_active": 1,
    "notes": null
  },
  {
    "name": 201,
    "rule_set": "TOPS-KNIT-BABY-EU-HEIGHT-REG",
    "pom": "POM-001",
    "increment_cm": 2.0,
    "grading_type": "LINEAR",
    "increment_above_xl": 2.0,
    "direction_note": "Baby EU: pit +4cm/talla.",
    "tolerance_check": "Tol. prod 1.0 ≤ grade 2.0",
    "client": null,
    "rule_source": "SECTOR_STANDARD",
    "is_active": 1,
    "notes": null
  },
  {
    "name": 200,
    "rule_set": "OUTERWEAR-MEN-EU-NUM-REG",
    "pom": "POM-093",
    "increment_cm": 0.0,
    "grading_type": "FIXED",
    "increment_above_xl": 0.0,
    "direction_note": "FIXED: partió no gradeja.",
    "tolerance_check": "N/A — FIXED",
    "client": null,
    "rule_source": "SECTOR_STANDARD",
    "is_active": 1,
    "notes": null
  },
  {
    "name": 199,
    "rule_set": "OUTERWEAR-MEN-EU-NUM-REG",
    "pom": "POM-101",
    "increment_cm": 0.0,
    "grading_type": "FIXED",
    "increment_above_xl": 0.0,
    "direction_note": "FIXED: solapa no gradeja.",
    "tolerance_check": "N/A — FIXED",
    "client": null,
    "rule_source": "SECTOR_STANDARD",
    "is_active": 1,
    "notes": null
  },
  {
    "name": 198,
    "rule_set": "OUTERWEAR-MEN-EU-NUM-REG",
    "pom": "POM-023",
    "increment_cm": 1.25,
    "grading_type": "LINEAR",
    "increment_above_xl": 1.25,
    "direction_note": "Bíceps outerwear: més que tops.",
    "tolerance_check": "Tol. prod 0.75 ≤ grade 1.25",
    "client": null,
    "rule_source": "SECTOR_STANDARD",
    "is_active": 1,
    "notes": null
  },
  {
    "name": 197,
    "rule_set": "OUTERWEAR-MEN-EU-NUM-REG",
    "pom": "POM-020",
    "increment_cm": 1.0,
    "grading_type": "LINEAR",
    "increment_above_xl": 1.0,
    "direction_note": "Outerwear: sleeve creix cada talla.",
    "tolerance_check": "Tol. prod 1.0 = grade — revisar",
    "client": null,
    "rule_source": "SECTOR_STANDARD",
    "is_active": 1,
    "notes": null
  },
  {
    "name": 196,
    "rule_set": "OUTERWEAR-MEN-EU-NUM-REG",
    "pom": "POM-010",
    "increment_cm": 1.0,
    "grading_type": "LINEAR",
    "increment_above_xl": 1.0,
    "direction_note": "CB length per a tailored outerwear.",
    "tolerance_check": "Tol. prod 1.5 > grade — OK",
    "client": null,
    "rule_source": "SECTOR_STANDARD",
    "is_active": 1,
    "notes": null
  },
  {
    "name": 195,
    "rule_set": "OUTERWEAR-MEN-EU-NUM-REG",
    "pom": "POM-009",
    "increment_cm": 1.0,
    "grading_type": "LINEAR",
    "increment_above_xl": 1.0,
    "direction_note": "Longitud creix cada talla.",
    "tolerance_check": "Tol. prod 1.5 > grade — OK",
    "client": null,
    "rule_source": "SECTOR_STANDARD",
    "is_active": 1,
    "notes": null
  },
  {
    "name": 194,
    "rule_set": "OUTERWEAR-MEN-EU-NUM-REG",
    "pom": "POM-005",
    "increment_cm": 0.5,
    "grading_type": "LINEAR",
    "increment_above_xl": 0.5,
    "direction_note": "Igual que tops.",
    "tolerance_check": "Tol. prod 0.75 > grade — OK",
    "client": null,
    "rule_source": "SECTOR_STANDARD",
    "is_active": 1,
    "notes": null
  },
  {
    "name": 193,
    "rule_set": "OUTERWEAR-MEN-EU-NUM-REG",
    "pom": "POM-001",
    "increment_cm": 2.5,
    "grading_type": "LINEAR",
    "increment_above_xl": 2.5,
    "direction_note": "Roba exterior: +0.5cm extra vs tops.",
    "tolerance_check": "Tol. prod 1.0 ≤ grade 2.5",
    "client": null,
    "rule_source": "SECTOR_STANDARD",
    "is_active": 1,
    "notes": null
  },
  {
    "name": 192,
    "rule_set": "BOTTOMS-MEN-PANTS-NUM-REG",
    "pom": "POM-052",
    "increment_cm": 0.0,
    "grading_type": "ZERO",
    "increment_above_xl": 0.0,
    "direction_note": "Alçada cinturó: no gradeja.",
    "tolerance_check": "N/A — ZERO",
    "client": null,
    "rule_source": "SECTOR_STANDARD",
    "is_active": 1,
    "notes": null
  },
  {
    "name": 191,
    "rule_set": "BOTTOMS-MEN-PANTS-NUM-REG",
    "pom": "POM-056",
    "increment_cm": 0.5,
    "grading_type": "LINEAR",
    "increment_above_xl": 0.5,
    "direction_note": "Cavall posterior igual que davanter.",
    "tolerance_check": "Tol. prod 0.75 > grade — OK",
    "client": null,
    "rule_source": "SECTOR_STANDARD",
    "is_active": 1,
    "notes": null
  },
  {
    "name": 190,
    "rule_set": "BOTTOMS-MEN-PANTS-NUM-REG",
    "pom": "POM-055",
    "increment_cm": 0.5,
    "grading_type": "LINEAR",
    "increment_above_xl": 0.5,
    "direction_note": "Cavall creix poc per talla.",
    "tolerance_check": "Tol. prod 0.75 > grade — OK",
    "client": null,
    "rule_source": "SECTOR_STANDARD",
    "is_active": 1,
    "notes": null
  },
  {
    "name": 189,
    "rule_set": "BOTTOMS-MEN-PANTS-NUM-REG",
    "pom": "POM-044",
    "increment_cm": 0.0,
    "grading_type": "ZERO",
    "increment_above_xl": 0.0,
    "direction_note": "ZERO: entrecuix NO gradeja.",
    "tolerance_check": "N/A — ZERO",
    "client": null,
    "rule_source": "SECTOR_STANDARD",
    "is_active": 1,
    "notes": null
  },
  {
    "name": 188,
    "rule_set": "BOTTOMS-MEN-PANTS-NUM-REG",
    "pom": "POM-043",
    "increment_cm": 0.5,
    "grading_type": "LINEAR",
    "increment_above_xl": 0.5,
    "direction_note": "Leg opening: creixement estètic.",
    "tolerance_check": "Tol. prod 0.75 > grade — OK",
    "client": null,
    "rule_source": "SECTOR_STANDARD",
    "is_active": 1,
    "notes": null
  },
  {
    "name": 187,
    "rule_set": "BOTTOMS-MEN-PANTS-NUM-REG",
    "pom": "POM-042",
    "increment_cm": 0.5,
    "grading_type": "LINEAR",
    "increment_above_xl": 0.5,
    "direction_note": "Genoll creix poc: silueta.",
    "tolerance_check": "Tol. prod 0.75 > grade — OK",
    "client": null,
    "rule_source": "SECTOR_STANDARD",
    "is_active": 1,
    "notes": null
  },
  {
    "name": 186,
    "rule_set": "BOTTOMS-MEN-PANTS-NUM-REG",
    "pom": "POM-041",
    "increment_cm": 1.0,
    "grading_type": "LINEAR",
    "increment_above_xl": 1.0,
    "direction_note": "Cuixa: ~50% del creixement de maluc.",
    "tolerance_check": "Tol. prod 0.75 ≤ grade 1.0",
    "client": null,
    "rule_source": "SECTOR_STANDARD",
    "is_active": 1,
    "notes": null
  },
  {
    "name": 185,
    "rule_set": "BOTTOMS-MEN-PANTS-NUM-REG",
    "pom": "POM-040",
    "increment_cm": 2.0,
    "grading_type": "LINEAR",
    "increment_above_xl": 2.0,
    "direction_note": "Maluc creix igual que cinturó.",
    "tolerance_check": "Tol. prod 1.0 ≤ grade 2.0",
    "client": null,
    "rule_source": "SECTOR_STANDARD",
    "is_active": 1,
    "notes": null
  },
  {
    "name": 184,
    "rule_set": "BOTTOMS-MEN-PANTS-NUM-REG",
    "pom": "POM-050",
    "increment_cm": 2.0,
    "grading_type": "LINEAR",
    "increment_above_xl": 2.0,
    "direction_note": "Cinturó = punt de partida grading.",
    "tolerance_check": "Tol. prod 1.0 ≤ grade 2.0",
    "client": null,
    "rule_source": "SECTOR_STANDARD",
    "is_active": 1,
    "notes": null
  },
  {
    "name": 183,
    "rule_set": "TOPS-WOVEN-MEN-EU-NUM-REG",
    "pom": "POM-030",
    "increment_cm": 0.0,
    "grading_type": "FIXED",
    "increment_above_xl": 0.0,
    "direction_note": "Coll camisa: SHIRT-NUM.",
    "tolerance_check": "N/A — FIXED",
    "client": null,
    "rule_source": "SECTOR_STANDARD",
    "is_active": 1,
    "notes": null
  },
  {
    "name": 182,
    "rule_set": "TOPS-WOVEN-MEN-EU-NUM-REG",
    "pom": "POM-025",
    "increment_cm": 0.0,
    "grading_type": "FIXED",
    "increment_above_xl": 0.0,
    "direction_note": "FIXED: puny formal no gradeja.",
    "tolerance_check": "N/A — FIXED",
    "client": null,
    "rule_source": "SECTOR_STANDARD",
    "is_active": 1,
    "notes": null
  },
  {
    "name": 181,
    "rule_set": "TOPS-WOVEN-MEN-EU-NUM-REG",
    "pom": "POM-023",
    "increment_cm": 1.0,
    "grading_type": "LINEAR",
    "increment_above_xl": 1.0,
    "direction_note": "Proporcional al pit.",
    "tolerance_check": "Tol. prod 0.75 ≤ grade 1.0",
    "client": null,
    "rule_source": "SECTOR_STANDARD",
    "is_active": 1,
    "notes": null
  },
  {
    "name": 180,
    "rule_set": "TOPS-WOVEN-MEN-EU-NUM-REG",
    "pom": "POM-020",
    "increment_cm": 1.0,
    "grading_type": "LINEAR",
    "increment_above_xl": 1.0,
    "direction_note": "Woven: màniga creix cada talla.",
    "tolerance_check": "Tol. prod 1.0 = grade — revisar",
    "client": null,
    "rule_source": "SECTOR_STANDARD",
    "is_active": 1,
    "notes": null
  },
  {
    "name": 179,
    "rule_set": "TOPS-WOVEN-MEN-EU-NUM-REG",
    "pom": "POM-012",
    "increment_cm": 0.75,
    "grading_type": "LINEAR",
    "increment_above_xl": 0.75,
    "direction_note": "Sisa woven igual que knitwear.",
    "tolerance_check": "Tol. prod 0.75 = grade — revisar",
    "client": null,
    "rule_source": "SECTOR_STANDARD",
    "is_active": 1,
    "notes": null
  },
  {
    "name": 178,
    "rule_set": "TOPS-WOVEN-MEN-EU-NUM-REG",
    "pom": "POM-009",
    "increment_cm": 1.0,
    "grading_type": "LINEAR",
    "increment_above_xl": 1.0,
    "direction_note": "Teixit pla: longitud creix cada talla.",
    "tolerance_check": "Tol. prod 1.5 > grade — OK",
    "client": null,
    "rule_source": "SECTOR_STANDARD",
    "is_active": 1,
    "notes": null
  },
  {
    "name": 177,
    "rule_set": "TOPS-WOVEN-MEN-EU-NUM-REG",
    "pom": "POM-005",
    "increment_cm": 0.5,
    "grading_type": "LINEAR",
    "increment_above_xl": 0.5,
    "direction_note": "Estàndard teixit pla home.",
    "tolerance_check": "Tol. prod 0.75 > grade — OK",
    "client": null,
    "rule_source": "SECTOR_STANDARD",
    "is_active": 1,
    "notes": null
  },
  {
    "name": 176,
    "rule_set": "TOPS-WOVEN-MEN-EU-NUM-REG",
    "pom": "POM-001",
    "increment_cm": 2.0,
    "grading_type": "LINEAR",
    "increment_above_xl": 2.0,
    "direction_note": "EU numeric: 4cm circumf.",
    "tolerance_check": "Tol. prod 1.0 ≤ grade 2.0",
    "client": null,
    "rule_source": "SECTOR_STANDARD",
    "is_active": 1,
    "notes": null
  },
  {
    "name": 175,
    "rule_set": "TOPS-KNIT-WOMEN-ALPHA-REG",
    "pom": "POM-030",
    "increment_cm": 0.25,
    "grading_type": "LINEAR",
    "increment_above_xl": 0.5,
    "direction_note": "EXCEPTION: coll quasi fix.",
    "tolerance_check": "Tol. prod 0.5 > grade — OK",
    "client": null,
    "rule_source": "SECTOR_STANDARD",
    "is_active": 1,
    "notes": null
  },
  {
    "name": 174,
    "rule_set": "TOPS-KNIT-WOMEN-ALPHA-REG",
    "pom": "POM-023",
    "increment_cm": 0.75,
    "grading_type": "LINEAR",
    "increment_above_xl": 1.0,
    "direction_note": "Dona: bíceps creix menys.",
    "tolerance_check": "Tol. prod 0.75 = grade — revisar",
    "client": null,
    "rule_source": "SECTOR_STANDARD",
    "is_active": 1,
    "notes": null
  },
  {
    "name": 173,
    "rule_set": "TOPS-KNIT-WOMEN-ALPHA-REG",
    "pom": "POM-020",
    "increment_cm": 0.75,
    "grading_type": "STEP",
    "increment_above_xl": 0.75,
    "direction_note": "Creixement per alçada.",
    "tolerance_check": "Tol. prod 1.0 > grade — OK",
    "client": null,
    "rule_source": "SECTOR_STANDARD",
    "is_active": 1,
    "notes": null
  },
  {
    "name": 172,
    "rule_set": "TOPS-KNIT-WOMEN-ALPHA-REG",
    "pom": "POM-009",
    "increment_cm": 1.5,
    "grading_type": "STEP",
    "increment_above_xl": 1.5,
    "direction_note": "Creix cada 2 talles adult.",
    "tolerance_check": "Tol. prod 1.5 = grade — revisar",
    "client": null,
    "rule_source": "SECTOR_STANDARD",
    "is_active": 1,
    "notes": null
  },
  {
    "name": 171,
    "rule_set": "TOPS-KNIT-WOMEN-ALPHA-REG",
    "pom": "POM-005",
    "increment_cm": 0.5,
    "grading_type": "LINEAR",
    "increment_above_xl": 0.5,
    "direction_note": "Espatlla creix limitat.",
    "tolerance_check": "Tol. prod 0.75 > grade — OK",
    "client": null,
    "rule_source": "SECTOR_STANDARD",
    "is_active": 1,
    "notes": null
  },
  {
    "name": 170,
    "rule_set": "TOPS-KNIT-WOMEN-ALPHA-REG",
    "pom": "POM-004",
    "increment_cm": 2.0,
    "grading_type": "LINEAR",
    "increment_above_xl": 2.5,
    "direction_note": "Maluc creix igual que pit.",
    "tolerance_check": "Tol. prod 1.0 ≤ grade 2.0",
    "client": null,
    "rule_source": "SECTOR_STANDARD",
    "is_active": 1,
    "notes": null
  },
  {
    "name": 169,
    "rule_set": "TOPS-KNIT-WOMEN-ALPHA-REG",
    "pom": "POM-003",
    "increment_cm": 2.0,
    "grading_type": "LINEAR",
    "increment_above_xl": 2.5,
    "direction_note": "Paral·lel al pit.",
    "tolerance_check": "Tol. prod 1.0 ≤ grade 2.0",
    "client": null,
    "rule_source": "SECTOR_STANDARD",
    "is_active": 1,
    "notes": null
  },
  {
    "name": 168,
    "rule_set": "TOPS-KNIT-WOMEN-ALPHA-REG",
    "pom": "POM-001",
    "increment_cm": 2.0,
    "grading_type": "LINEAR",
    "increment_above_xl": 2.5,
    "direction_note": "EU dona: 4cm circumf (2cm flat).",
    "tolerance_check": "Tol. prod 1.0 ≤ grade 2.0",
    "client": null,
    "rule_source": "SECTOR_STANDARD",
    "is_active": 1,
    "notes": null
  },
  {
    "name": 167,
    "rule_set": "TOPS-KNIT-MEN-ALPHA-REG",
    "pom": "POM-070",
    "increment_cm": 2.5,
    "grading_type": "LINEAR",
    "increment_above_xl": 3.0,
    "direction_note": "Baix = pit en tops rectes.",
    "tolerance_check": "Tol. prod 1.5 ≤ grade 2.5",
    "client": null,
    "rule_source": "SECTOR_STANDARD",
    "is_active": 1,
    "notes": null
  },
  {
    "name": 166,
    "rule_set": "TOPS-KNIT-MEN-ALPHA-REG",
    "pom": "POM-031",
    "increment_cm": 0.25,
    "grading_type": "STEP",
    "increment_above_xl": 0.25,
    "direction_note": "Caiguda escot: quasi FIXED.",
    "tolerance_check": "Tol. prod 0.5 > grade — OK",
    "client": null,
    "rule_source": "SECTOR_STANDARD",
    "is_active": 1,
    "notes": null
  },
  {
    "name": 165,
    "rule_set": "TOPS-KNIT-MEN-ALPHA-REG",
    "pom": "POM-030",
    "increment_cm": 0.25,
    "grading_type": "LINEAR",
    "increment_above_xl": 0.5,
    "direction_note": "Coll creix molt poc.",
    "tolerance_check": "Tol. prod 0.5 > grade — OK",
    "client": null,
    "rule_source": "SECTOR_STANDARD",
    "is_active": 1,
    "notes": null
  },
  {
    "name": 164,
    "rule_set": "TOPS-KNIT-MEN-ALPHA-REG",
    "pom": "POM-025",
    "increment_cm": 0.5,
    "grading_type": "LINEAR",
    "increment_above_xl": 0.5,
    "direction_note": "Puny creix però menys que bíceps.",
    "tolerance_check": "Tol. prod 0.5 = grade — revisar",
    "client": null,
    "rule_source": "SECTOR_STANDARD",
    "is_active": 1,
    "notes": null
  },
  {
    "name": 163,
    "rule_set": "TOPS-KNIT-MEN-ALPHA-REG",
    "pom": "POM-023",
    "increment_cm": 1.0,
    "grading_type": "LINEAR",
    "increment_above_xl": 1.0,
    "direction_note": "Bíceps ~40% del creixement de pit.",
    "tolerance_check": "Tol. prod 0.75 ≤ grade 1.0",
    "client": null,
    "rule_source": "SECTOR_STANDARD",
    "is_active": 1,
    "notes": null
  },
  {
    "name": 162,
    "rule_set": "TOPS-KNIT-MEN-ALPHA-REG",
    "pom": "POM-020",
    "increment_cm": 0.75,
    "grading_type": "STEP",
    "increment_above_xl": 0.75,
    "direction_note": "Màniga: creixement per alçada.",
    "tolerance_check": "Tol. prod 1.0 > grade — OK",
    "client": null,
    "rule_source": "SECTOR_STANDARD",
    "is_active": 1,
    "notes": null
  },
  {
    "name": 161,
    "rule_set": "TOPS-KNIT-MEN-ALPHA-REG",
    "pom": "POM-012",
    "increment_cm": 0.75,
    "grading_type": "LINEAR",
    "increment_above_xl": 0.75,
    "direction_note": "Sisa creix menys que pit.",
    "tolerance_check": "Tol. prod 0.75 = grade — OK",
    "client": null,
    "rule_source": "SECTOR_STANDARD",
    "is_active": 1,
    "notes": null
  },
  {
    "name": 160,
    "rule_set": "TOPS-KNIT-MEN-ALPHA-REG",
    "pom": "POM-009",
    "increment_cm": 1.5,
    "grading_type": "STEP",
    "increment_above_xl": 1.5,
    "direction_note": "Creix cada 2 talles en alpha adult.",
    "tolerance_check": "Tol. prod 1.5 = grade — revisar",
    "client": null,
    "rule_source": "SECTOR_STANDARD",
    "is_active": 1,
    "notes": null
  },
  {
    "name": 159,
    "rule_set": "TOPS-KNIT-MEN-ALPHA-REG",
    "pom": "POM-005",
    "increment_cm": 0.5,
    "grading_type": "LINEAR",
    "increment_above_xl": 0.5,
    "direction_note": "Espatlla creix molt limitat.",
    "tolerance_check": "Tol. prod 0.75 > grade — OK",
    "client": null,
    "rule_source": "SECTOR_STANDARD",
    "is_active": 1,
    "notes": null
  },
  {
    "name": 158,
    "rule_set": "TOPS-KNIT-MEN-ALPHA-REG",
    "pom": "POM-003",
    "increment_cm": 2.5,
    "grading_type": "LINEAR",
    "increment_above_xl": 3.0,
    "direction_note": "Paral·lel al pit en tops",
    "tolerance_check": "Tol. prod 1.0 ≤ grade 2.5",
    "client": null,
    "rule_source": "SECTOR_STANDARD",
    "is_active": 1,
    "notes": null
  },
  {
    "name": 157,
    "rule_set": "TOPS-KNIT-MEN-ALPHA-REG",
    "pom": "POM-001",
    "increment_cm": 2.5,
    "grading_type": "LINEAR",
    "increment_above_xl": 3.0,
    "direction_note": "Cada talla +2.5cm flat. >XL: +3.0cm",
    "tolerance_check": "Tol. prod 1.0 ≤ grade 2.5",
    "client": null,
    "rule_source": "SECTOR_STANDARD",
    "is_active": 1,
    "notes": null
  }
]